LICENSE
NOTICE
README.md
setup.py
sonne/__init__.py
sonne/__main__.py
sonne.egg-info/PKG-INFO
sonne.egg-info/SOURCES.txt
sonne.egg-info/dependency_links.txt
sonne.egg-info/top_level.txt